<?xml version="1.0" encoding="UTF-8"?>
<images>
  <image path="/images/accept.png" width="16" height="16"/>
  <image path="/images/add.png" width="16" height="16"/>
  <image path="/images/appleTouchIcon.png" width="114" height="114"/>
  <image path="/images/arrow-down.png" width="16" height="16"/>
  <image path="/images/arrow_undo.png" width="16" height="16"/>
  <image path="/images/asteriskOperatorPanel.png" width="137" height="76"/>
  <image path="/images/attach.png" width="16" height="16"/>
  <image path="/images/background.gif" width="975" height="22"/>
  <image path="/images/blank.gif" width="1" height="1"/>
  <image path="/images/book_add.png" width="16" height="16"/>
  <image path="/images/book_delete.png" width="16" height="16"/>
  <image path="/images/book_edit.png" width="16" height="16"/>
  <image path="/images/book_open.png" width="16" height="16"/>
  <image path="/images/brick.png" width="16" height="16"/>
  <image path="/images/bricks.png" width="16" height="16"/>
  <image path="/images/building_add.png" width="16" height="16"/>
  <image path="/images/building_delete.png" width="16" height="16"/>
  <image path="/images/building_edit.png" width="16" height="16"/>
  <image path="/images/bullet_star.png" width="16" height="16"/>
  <image path="/images/button_assignToLeft.png" width="16" height="16"/>
  <image path="/images/button_assignToRight.png" width="16" height="16"/>
  <image path="/images/button_calendar_day.png" width="16" height="16"/>
  <image path="/images/button_calendar_month.png" width="16" height="16"/>
  <image path="/images/button_calendar_week.png" width="16" height="16"/>
  <image path="/images/button_cancel.png" width="16" height="16"/>
  <image path="/images/button_date_next.png" width="16" height="16"/>
  <image path="/images/button_date_previous.png" width="16" height="16"/>
  <image path="/images/button_left.png" width="16" height="16"/>
  <image path="/images/button_next_month.png" width="16" height="16"/>
  <image path="/images/button_next_week.png" width="16" height="16"/>
  <image path="/images/button_previous_month.png" width="16" height="16"/>
  <image path="/images/button_previous_week.png" width="16" height="16"/>
  <image path="/images/button_reload.png" width="16" height="16"/>
  <image path="/images/button_right.png" width="16" height="16"/>
  <image path="/images/button_selectCustomer.png" width="16" height="16"/>
  <image path="/images/button_selectDate.png" width="16" height="16"/>
  <image path="/images/button_selectGroup.png" width="16" height="16"/>
  <image path="/images/button_selectMe.png" width="16" height="16"/>
  <image path="/images/button_selectProjekt.png" width="16" height="16"/>
  <image path="/images/button_selectTask.png" width="16" height="16"/>
  <image path="/images/button_selectUser.png" width="16" height="16"/>
  <image path="/images/button_unselect.gif" width="16" height="16"/>
  <image path="/images/button_unselectCustomer.png" width="16" height="16"/>
  <image path="/images/button_unselectDate.png" width="16" height="16"/>
  <image path="/images/button_unselectGroup.png" width="16" height="16"/>
  <image path="/images/button_unselectProjekt.png" width="16" height="16"/>
  <image path="/images/button_unselectTask.png" width="16" height="16"/>
  <image path="/images/button_unselectUser.png" width="16" height="16"/>
  <image path="/images/cake.png" width="16" height="16"/>
  <image path="/images/cake_delete.png" width="16" height="16"/>
  <image path="/images/calculator.png" width="16" height="16"/>
  <image path="/images/calculator_add.png" width="16" height="16"/>
  <image path="/images/calculator_edit.png" width="16" height="16"/>
  <image path="/images/calendar.png" width="16" height="16"/>
  <image path="/images/cart.png" width="16" height="16"/>
  <image path="/images/chart_line.png" width="16" height="16"/>
  <image path="/images/chart_organisation.png" width="16" height="16"/>
  <image path="/images/clock.png" width="16" height="16"/>
  <image path="/images/clock_add.png" width="16" height="16"/>
  <image path="/images/clock_delete.png" width="16" height="16"/>
  <image path="/images/clock_edit.png" width="16" height="16"/>
  <image path="/images/cog.png" width="16" height="16"/>
  <image path="/images/coins.png" width="16" height="16"/>
  <image path="/images/coins_add.png" width="16" height="16"/>
  <image path="/images/coins_delete.png" width="16" height="16"/>
  <image path="/images/coins_edit.png" width="16" height="16"/>
  <image path="/images/comment.png" width="16" height="16"/>
  <image path="/images/css_img/body_bg.gif" width="16" height="1200"/>
  <image path="/images/css_img/buttonLeftAc.png" width="31" height="20"/>
  <image path="/images/css_img/buttonLeftActive.png" width="31" height="20"/>
  <image path="/images/css_img/buttonLeftIn.png" width="31" height="20"/>
  <image path="/images/css_img/buttonLeftInactive.png" width="31" height="20"/>
  <image path="/images/css_img/buttonRightActive.png" width="149" height="20"/>
  <image path="/images/css_img/buttonRightInactive.png" width="149" height="20"/>
  <image path="/images/css_img/centerActive.png" width="136" height="20"/>
  <image path="/images/css_img/centerInactive.png" width="136" height="20"/>
  <image path="/images/css_img/form_bg.gif" width="25" height="16"/>
  <image path="/images/css_img/gradient_32.png" width="32" height="32"/>
  <image path="/images/css_img/grid.gif" width="16" height="16"/>
  <image path="/images/css_img/hr.gif" width="32" height="15"/>
  <image path="/images/css_img/indicator.gif" width="16" height="16"/>
  <image path="/images/css_img/leftActive.png" width="21" height="20"/>
  <image path="/images/css_img/leftInactive.png" width="21" height="20"/>
  <image path="/images/css_img/rightActive.png" width="21" height="20"/>
  <image path="/images/css_img/rightInactive.png" width="21" height="20"/>
  <image path="/images/css_img/sort.png" width="16" height="15"/>
  <image path="/images/css_img/sort_asc.png" width="16" height="15"/>
  <image path="/images/css_img/sort_desc.png" width="16" height="15"/>
  <image path="/images/cup.png" width="16" height="16"/>
  <image path="/images/customer.png" width="16" height="16"/>
  <image path="/images/database_delete.png" width="16" height="16"/>
  <image path="/images/database_insert.png" width="16" height="16"/>
  <image path="/images/database_refresh.png" width="16" height="16"/>
  <image path="/images/database_select.png" width="16" height="16"/>
  <image path="/images/database_update.png" width="16" height="16"/>
  <image path="/images/deny.png" width="16" height="16"/>
  <image path="/images/door_in.png" width="16" height="16"/>
  <image path="/images/door_out.png" width="16" height="16"/>
  <image path="/images/exclamation.png" width="16" height="16"/>
  <image path="/images/explosion.gif" width="19" height="15"/>
  <image path="/images/eye.png" width="16" height="16"/>
  <image path="/images/find.png" width="16" height="16"/>
  <image path="/images/folder.gif" width="19" height="15"/>
  <image path="/images/folder_open.gif" width="19" height="15"/>
  <image path="/images/gantt.png" width="16" height="16"/>
  <image path="/images/group.png" width="16" height="16"/>
  <image path="/images/group_add.png" width="16" height="16"/>
  <image path="/images/group_delete.png" width="16" height="16"/>
  <image path="/images/group_edit.png" width="16" height="16"/>
  <image path="/images/help.png" width="16" height="16"/>
  <image path="/images/holiday.png" width="16" height="16"/>
  <image path="/images/house.png" width="16" height="16"/>
  <image path="/images/images.png" width="16" height="16"/>
  <image path="/images/info.png" width="16" height="16"/>
  <image path="/images/information.png" width="16" height="16"/>
  <image path="/images/key.png" width="16" height="16"/>
  <image path="/images/keyboard.png" width="16" height="16"/>
  <image path="/images/kost2art.png" width="16" height="16"/>
  <image path="/images/leaf.gif" width="19" height="15"/>
  <image path="/images/lock.png" width="16" height="16"/>
  <image path="/images/lock_add.png" width="16" height="16"/>
  <image path="/images/lock_delete.png" width="16" height="16"/>
  <image path="/images/lock_edit.png" width="16" height="16"/>
  <image path="/images/loginheader.png" width="330" height="108"/>
  <image path="/images/logo-top-right.png" width="65" height="43"/>
  <image path="/images/mail_open.png" width="16" height="16"/>
  <image path="/images/mail_out.png" width="16" height="16"/>
  <image path="/images/meb.png" width="16" height="16"/>
  <image path="/images/menuTree/empty.gif" width="18" height="18"/>
  <image path="/images/menuTree/join.gif" width="18" height="18"/>
  <image path="/images/menuTree/joinbottom.gif" width="18" height="18"/>
  <image path="/images/menuTree/line.gif" width="18" height="18"/>
  <image path="/images/menuTree/minus.gif" width="18" height="18"/>
  <image path="/images/menuTree/minusbottom.gif" width="18" height="18"/>
  <image path="/images/menuTree/plus.gif" width="18" height="18"/>
  <image path="/images/menuTree/plusbottom.gif" width="18" height="18"/>
  <image path="/images/Micromata.gif" width="518" height="104"/>
  <image path="/images/micromata_icon.png" width="14" height="13"/>
  <image path="/images/money.png" width="16" height="16"/>
  <image path="/images/money_add.png" width="16" height="16"/>
  <image path="/images/money_delete.png" width="16" height="16"/>
  <image path="/images/money_edit.png" width="16" height="16"/>
  <image path="/images/new.png" width="16" height="16"/>
  <image path="/images/newspaper.png" width="16" height="16"/>
  <image path="/images/page.gif" width="18" height="18"/>
  <image path="/images/page_copy.png" width="16" height="16"/>
  <image path="/images/page_msproject.png" width="16" height="16"/>
  <image path="/images/page_paste.png" width="16" height="16"/>
  <image path="/images/page_svg.png" width="16" height="16"/>
  <image path="/images/page_white.png" width="16" height="16"/>
  <image path="/images/page_white_acrobat.png" width="16" height="16"/>
  <image path="/images/page_white_cup.png" width="16" height="16"/>
  <image path="/images/page_white_excel.png" width="16" height="16"/>
  <image path="/images/pencil.png" width="16" height="16"/>
  <image path="/images/phone.png" width="16" height="16"/>
  <image path="/images/plugin_add.png" width="16" height="16"/>
  <image path="/images/plugin_delete.png" width="16" height="16"/>
  <image path="/images/plugin_edit.png" width="16" height="16"/>
  <image path="/images/printer.png" width="16" height="16"/>
  <image path="/images/projectforge.png" width="16" height="16"/>
  <image path="/images/projekt.png" width="16" height="16"/>
  <image path="/images/report_add.png" width="16" height="16"/>
  <image path="/images/report_delete.png" width="16" height="16"/>
  <image path="/images/report_disk.png" width="16" height="16"/>
  <image path="/images/report_edit.png" width="16" height="16"/>
  <image path="/images/report_magnify.png" width="16" height="16"/>
  <image path="/images/report_user.png" width="16" height="16"/>
  <image path="/images/resultset_first.png" width="16" height="16"/>
  <image path="/images/resultset_last.png" width="16" height="16"/>
  <image path="/images/resultset_next.png" width="16" height="16"/>
  <image path="/images/resultset_previous.png" width="16" height="16"/>
  <image path="/images/row_pointer.png" width="8" height="13"/>
  <image path="/images/script.png" width="16" height="16"/>
  <image path="/images/script_add.png" width="16" height="16"/>
  <image path="/images/script_delete.png" width="16" height="16"/>
  <image path="/images/script_edit.png" width="16" height="16"/>
  <image path="/images/script_gear.png" width="16" height="16"/>
  <image path="/images/script_lightning.png" width="16" height="16"/>
  <image path="/images/server_chart.png" width="16" height="16"/>
  <image path="/images/sms.png" width="23" height="16"/>
  <image path="/images/spacer.gif" width="1" height="1"/>
  <image path="/images/star_plus.png" width="20" height="20"/>
  <image path="/images/table_row_insert.png" width="16" height="16"/>
  <image path="/images/tag_blue_add.png" width="16" height="16"/>
  <image path="/images/tag_blue_delete.png" width="16" height="16"/>
  <image path="/images/tag_blue_edit.png" width="16" height="16"/>
  <image path="/images/task_add.png" width="16" height="16"/>
  <image path="/images/task_delete.png" width="16" height="16"/>
  <image path="/images/task_edit.png" width="16" height="16"/>
  <image path="/images/telephone.png" width="16" height="16"/>
  <image path="/images/trash.png" width="16" height="16"/>
  <image path="/images/user.png" width="16" height="16"/>
  <image path="/images/user_add.png" width="16" height="16"/>
  <image path="/images/user_delete.png" width="16" height="16"/>
  <image path="/images/user_edit.png" width="16" height="16"/>
  <image path="/images/user_red.png" width="16" height="16"/>
  <image path="/images/vcard.png" width="16" height="16"/>
  <image path="/images/vcard_add.png" width="16" height="16"/>
  <image path="/images/vcard_delete.png" width="16" height="16"/>
  <image path="/images/vcard_edit.png" width="16" height="16"/>
  <image path="/images/wand.png" width="16" height="16"/>
  <image path="/images/zoom.png" width="16" height="16"/>
  <image path="/images/zoom_in.png" width="16" height="16"/>
  <image path="/images/zoom_out.png" width="16" height="16"/>
  <image path="/mobile/jquery.mobile/images/ajax-loader.png" width="35" height="35"/>
  <image path="/mobile/jquery.mobile/images/form-check-off.png" width="20" height="20"/>
  <image path="/mobile/jquery.mobile/images/form-check-on.png" width="20" height="20"/>
  <image path="/mobile/jquery.mobile/images/form-radio-off.png" width="20" height="20"/>
  <image path="/mobile/jquery.mobile/images/form-radio-on.png" width="20" height="20"/>
  <image path="/mobile/jquery.mobile/images/icon-search-black.png" width="16" height="16"/>
  <image path="/mobile/jquery.mobile/images/icons-18-black.png" width="560" height="20"/>
  <image path="/mobile/jquery.mobile/images/icons-18-white.png" width="558" height="18"/>
  <image path="/mobile/jquery.mobile/images/icons-36-black.png" width="1116" height="36"/>
  <image path="/mobile/jquery.mobile/images/icons-36-white.png" width="1116" height="36"/>
</images>